<?xml version='1.0' encoding='UTF-8'?>
<annotation>
  <filename>1647844803.9503036.jpeg</filename>
  <object_num>2</object_num>
  <size>
    <width>113</width>
    <height>277</height>
  </size>
  <object>
    <name>phone</name>
    <difficult>0</difficult>
    <bndbox>
      <xmin>6</xmin>
      <ymin>5</ymin>
      <xmax>89</xmax>
      <ymax>78</ymax>
    </bndbox>
  </object>
  <object>
    <name>phone</name>
    <difficult>0</difficult>
    <bndbox>
      <xmin>1</xmin>
      <ymin>180</ymin>
      <xmax>58</xmax>
      <ymax>270</ymax>
    </bndbox>
  </object>
</annotation>
